dextrusion/DeXtrusion.py
dextrusion/DialogDeXtrusion.py
dextrusion/DialogParameters.py
dextrusion/MovieGeneratorFromROI.py
dextrusion/Network.py
dextrusion/RoiUtils.py
dextrusion/__init__.py
dextrusion/__main__.py
dextrusion-0.0.8.dist-info/LICENSE
dextrusion-0.0.8.dist-info/METADATA
dextrusion-0.0.8.dist-info/WHEEL
dextrusion-0.0.8.dist-info/top_level.txt
dextrusion-0.0.8.dist-info/RECORD
